{"version":"0.1.0","name":"lima-limon","dependencies":{"@headlessui/react":{"version":"1.7.14"},"@heroicons/react":{"version":"2.0.17"},"@prisma/client":{"version":"4.14.1"},"@types/node":{"version":"18.15.11"},"@types/react-dom":{"version":"18.0.11"},"@types/react":{"version":"18.0.34"},"autoprefixer":{"version":"10.4.14"},"daisyui":{"version":"2.51.6"},"eslint-config-next":{"version":"13.4.3"},"eslint":{"version":"8.38.0"},"heroicons":{"version":"2.0.17"},"next":{"version":"13.4.3"},"postcss":{"version":"8.4.21"},"react-dom":{"version":"18.2.0"},"react-hook-form":{"version":"7.43.9"},"react-icons":{"version":"4.8.0"},"react-select":{"version":"5.7.2"},"react":{"version":"18.2.0"},"tailwindcss":{"version":"3.3.1"},"typescript":{"version":"5.0.4"}}}